.DS_Store
AD/DualNumber.py
AD/ElementaryFunctions.py
AD/Parallelized.py
AD/__init__.py
AD/tests.py
autodiffing-0.0.7.dist-info/LICENSE
autodiffing-0.0.7.dist-info/METADATA
autodiffing-0.0.7.dist-info/WHEEL
autodiffing-0.0.7.dist-info/top_level.txt
autodiffing-0.0.7.dist-info/RECORD
