Metadata-Version: 2.1
Name: autodiffing
Version: 0.0.7
Summary: A package for Automatic Differentiation
Home-page: https://github.com/AutoDiffingFall2019/cs207-FinalProject
Author: Shuvom, Sijie, Silin, Edwin
Author-email: ssadhuka@college.harvard.edu, sijiesun@g.harvard.edu, szou@g.harvard.edu, chng_weimingedwin@g.harvard.edu
License: UNKNOWN
Platform: UNKNOWN
Classifier: Programming Language :: Python :: 3
Classifier: License :: OSI Approved :: MIT License
Classifier: Operating System :: OS Independent
Requires-Python: >=3.7
Requires-Dist: atomicwrites (==1.3.0)
Requires-Dist: attrs (==19.3.0)
Requires-Dist: bleach (==3.1.0)
Requires-Dist: certifi (==2019.9.11)
Requires-Dist: chardet (==3.0.4)
Requires-Dist: coverage (==4.5.4)
Requires-Dist: cycler (==0.10.0)
Requires-Dist: doctest-cli (==0.0.3)
Requires-Dist: docutils (==0.15.2)
Requires-Dist: idna (==2.8)
Requires-Dist: importlib-metadata (==0.23)
Requires-Dist: kiwisolver (==1.1.0)
Requires-Dist: matplotlib (==3.1.1)
Requires-Dist: more-itertools (==7.2.0)
Requires-Dist: nltk (==3.4.5)
Requires-Dist: numpy (==1.17.4)
Requires-Dist: packaging (==19.2)
Requires-Dist: pkginfo (==1.5.0.1)
Requires-Dist: pluggy (==0.13.0)
Requires-Dist: py (==1.8.0)
Requires-Dist: Pygments (==2.4.2)
Requires-Dist: pyparsing (==2.4.5)
Requires-Dist: pytest (==5.2.4)
Requires-Dist: pytest-cov (==2.8.1)
Requires-Dist: python-dateutil (==2.8.1)
Requires-Dist: readme-renderer (==24.0)
Requires-Dist: requests (==2.22.0)
Requires-Dist: requests-toolbelt (==0.9.1)
Requires-Dist: scipy (==1.3.2)
Requires-Dist: six (==1.13.0)
Requires-Dist: tqdm (==4.38.0)
Requires-Dist: twine (==2.0.0)
Requires-Dist: urllib3 (==1.25.7)
Requires-Dist: wcwidth (==0.1.7)
Requires-Dist: webencodings (==0.5.1)
Requires-Dist: zipp (==0.6.0)
